{
  "$schema": "https://typedoc.org/schema.json",
  "entryPoints": ["src/index.ts"],
  "tsconfig": "tsconfig.json",
  "out": "docs/api",
  "name": "light-runner",
  "readme": "none",
  "includeVersion": true,
  "excludeInternal": true,
  "excludePrivate": true,
  "excludeProtected": false,
  "disableSources": false,
  "githubPages": true,
  "hideGenerator": false,
  "navigationLinks": {
    "Homepage": "https://enixcode.github.io/light-runner/",
    "GitHub": "https://github.com/enixCode/light-runner",
    "npm": "https://www.npmjs.com/package/light-runner"
  },
  "sidebarLinks": {
    "Main site": "../index.html"
  }
}
